LICENSE
README.md
requirements.txt
setup.py
scalebar/__init__.py
scalebar/_version.py
scalebar/estimate.py
scalebar/example.py
scalebar/visualize.py
scalebar.egg-info/PKG-INFO
scalebar.egg-info/SOURCES.txt
scalebar.egg-info/dependency_links.txt
scalebar.egg-info/not-zip-safe
scalebar.egg-info/requires.txt
scalebar.egg-info/top_level.txt
scalebar/core/__init__.py
scalebar/core/bounding_box.py
scalebar/core/estimation.py
scalebar/core/image_wrapper.py
scalebar/core/position.py
scalebar/core/size.py
scalebar/utils/__init__.py
scalebar/utils/corner_ops.py
scalebar/utils/image_ops.py
scalebar/utils/pattern.py