Metadata-Version: 2.1
Name: scalebar
Version: 0.5.3
Summary: Processing tools for scale bars in images.
Author: Dimitri Korsch
Author-email: korschdima@gmail.com
License: AGPL-3.0 License
License-File: LICENSE
Requires-Dist: opencv-python-headless
Requires-Dist: scikit-image
Requires-Dist: scikit-learn
Requires-Dist: numpy
